{"timestamp": "2022-10-25T01:40:39Z", "previous_timestamp": "2022-10-25T01:35:39Z", "next_timestamp": "2022-10-25T01:45:39Z", "data": [{"id": "2fd979c0fe748488ae279bee42623bdf", "sport_key": "icehockey_nhl", "sport_title": "NHL", "commence_time": "2022-10-24T23:00:00Z", "home_team": "Ottawa Senators", "away_team": "Dallas Stars", "bookmakers": []}, {"id": "d8113a02d187ec82154ab55969139968", "sport_key": "icehockey_nhl", "sport_title": "NHL", "commence_time": "2022-10-24T23:00:00Z", "home_team": "New Jersey Devils", "away_team": "Washington Capitals", "bookmakers": []}, {"id": "b245b9c4e7420059900f3802d73051f8", "sport_key": "icehockey_nhl", "sport_title": "NHL", "commence_time": "2022-10-25T00:00:00Z", "home_team": "Edmonton Oilers", "away_team": "Pittsburgh Penguins", "bookmakers": []}, {"id": "14f6c0eeaacb10dcca626ef67a60b74d", "sport_key": "icehockey_nhl", "sport_title": "NHL", "commence_time": "2022-10-25T00:00:00Z", "home_team": "Winnipeg Jets", "away_team": "St Louis Blues", "bookmakers": []}, {"id": "b5c3d84605882891fc05d8950339c92c", "sport_key": "icehockey_nhl", "sport_title": "NHL", "commence_time": "2022-10-25T02:00:00Z", "home_team": "Vegas Golden Knights", "away_team": "Toronto Maple Leafs", "bookmakers": []}, {"id": "c0e322329a5033efc3682bcf512e66e6", "sport_key": "icehockey_nhl", "sport_title": "NHL", "commence_time": "2022-10-25T02:30:00Z", "home_team": "Vancouver Canucks", "away_team": "Carolina Hurricanes", "bookmakers": []}, {"id": "5b84552ae7ec5ec9eabd290daf3e2e24", "sport_key": "icehockey_nhl", "sport_title": "NHL", "commence_time": "2022-10-25T23:00:00Z", "home_team": "Columbus Blue Jackets", "away_team": "Arizona Coyotes", "bookmakers": []}, {"id": "e155753ef1acaf81f7710c9bb8804c92", "sport_key": "icehockey_nhl", "sport_title": "NHL", "commence_time": "2022-10-25T23:00:00Z", "home_team": "Boston Bruins", "away_team": "Dallas Stars", "bookmakers": []}, {"id": "d3c8927b600370074a3511935db9a166", "sport_key": "icehockey_nhl", "sport_title": "NHL", "commence_time": "2022-10-25T23:00:00Z", "home_team": "Detroit Red Wings", "away_team": "New Jersey Devils", "bookmakers": []}, {"id": "e62dc198eca23fab0760fb98f32ee198", "sport_key": "icehockey_nhl", "sport_title": "NHL", "commence_time": "2022-10-25T23:00:00Z", "home_team": "Montr\u00e9al Canadiens", "away_team": "Minnesota Wild", "bookmakers": []}, {"id": "635a8a5c7f9b7d5f8bde71a30840271d", "sport_key": "icehockey_nhl", "sport_title": "NHL", "commence_time": "2022-10-26T00:00:00Z", "home_team": "New York Rangers", "away_team": "Colorado Avalanche", "bookmakers": []}, {"id": "e938464ad6971fe1f57a5239c01246e8", "sport_key": "icehockey_nhl", "sport_title": "NHL", "commence_time": "2022-10-26T00:30:00Z", "home_team": "Chicago Blackhawks", "away_team": "Florida Panthers", "bookmakers": []}, {"id": "586ec2a3264fb0655a88e9abab83427b", "sport_key": "icehockey_nhl", "sport_title": "NHL", "commence_time": "2022-10-26T01:00:00Z", "home_team": "Calgary Flames", "away_team": "Pittsburgh Penguins", "bookmakers": []}, {"id": "1d21fc9d2363c88809c14dfdcb9726c1", "sport_key": "icehockey_nhl", "sport_title": "NHL", "commence_time": "2022-10-26T02:00:00Z", "home_team": "Seattle Kraken", "away_team": "Buffalo Sabres", "bookmakers": []}, {"id": "95b1d65d4b1ac041da8aa95de15a8ef1", "sport_key": "icehockey_nhl", "sport_title": "NHL", "commence_time": "2022-10-26T02:30:00Z", "home_team": "Los Angeles Kings", "away_team": "Tampa Bay Lightning", "bookmakers": []}, {"id": "facea467c5eb55735d6d0fc143b9cb2f", "sport_key": "icehockey_nhl", "sport_title": "NHL", "commence_time": "2022-10-26T02:30:00Z", "home_team": "San Jose Sharks", "away_team": "Vegas Golden Knights", "bookmakers": []}]}