{"timestamp": "2025-05-09T16:55:38Z", "previous_timestamp": "2025-05-09T16:50:38Z", "next_timestamp": "2025-05-09T17:00:38Z", "data": [{"id": "e88a97a8ecd3785abe25c00c5a393484", "sport_key": "icehockey_nhl", "sport_title": "NHL", "commence_time": "2025-05-09T23:00:00Z", "home_team": "Florida Panthers", "away_team": "Toronto Maple Leafs"}, {"id": "ddec7c2e25102932bd886e837fc2b2ce", "sport_key": "icehockey_nhl", "sport_title": "NHL", "commence_time": "2025-05-10T01:40:00Z", "home_team": "Winnipeg Jets", "away_team": "Dallas Stars"}, {"id": "3c8b9a936d0d6bab6bef5d497aedde9f", "sport_key": "icehockey_nhl", "sport_title": "NHL", "commence_time": "2025-05-10T22:10:00Z", "home_team": "Carolina Hurricanes", "away_team": "Washington Capitals"}, {"id": "0804798016d50211ab9298d8abf13aa5", "sport_key": "icehockey_nhl", "sport_title": "NHL", "commence_time": "2025-05-11T01:10:00Z", "home_team": "Edmonton Oilers", "away_team": "Vegas Golden Knights"}]}