{"timestamp": "2023-12-01T16:55:39Z", "previous_timestamp": "2023-12-01T16:50:39Z", "next_timestamp": "2023-12-01T17:00:39Z", "data": [{"id": "cef27c60f2240b1b77a67a40218b09eb", "sport_key": "icehockey_nhl", "sport_title": "NHL", "commence_time": "2023-12-02T00:00:00Z", "home_team": "Columbus Blue Jackets", "away_team": "Ottawa Senators"}, {"id": "e18c291d22086571f89a2915ecd0ea5d", "sport_key": "icehockey_nhl", "sport_title": "NHL", "commence_time": "2023-12-02T00:00:00Z", "home_team": "New Jersey Devils", "away_team": "San Jose Sharks"}, {"id": "679071992735741aa6e7fb82bf15590c", "sport_key": "icehockey_nhl", "sport_title": "NHL", "commence_time": "2023-12-02T19:00:00Z", "home_team": "Dallas Stars", "away_team": "Tampa Bay Lightning"}, {"id": "1ec394cc89654cd2cb7c4324e2077cb4", "sport_key": "icehockey_nhl", "sport_title": "NHL", "commence_time": "2023-12-02T20:00:00Z", "home_team": "Winnipeg Jets", "away_team": "Chicago Blackhawks"}, {"id": "7b1a663692131951060b0093373ea0bb", "sport_key": "icehockey_nhl", "sport_title": "NHL", "commence_time": "2023-12-02T21:30:00Z", "home_team": "Nashville Predators", "away_team": "New York Rangers"}, {"id": "ad80dcd9bf52f1e9888181b95b10c122", "sport_key": "icehockey_nhl", "sport_title": "NHL", "commence_time": "2023-12-02T23:00:00Z", "home_team": "Florida Panthers", "away_team": "New York Islanders"}, {"id": "7e15790e7b1819c480954121ad3644d0", "sport_key": "icehockey_nhl", "sport_title": "NHL", "commence_time": "2023-12-03T00:00:00Z", "home_team": "Toronto Maple Leafs", "away_team": "Boston Bruins"}, {"id": "dca016d38db7b2484341816c435cba86", "sport_key": "icehockey_nhl", "sport_title": "NHL", "commence_time": "2023-12-03T00:00:00Z", "home_team": "Carolina Hurricanes", "away_team": "Buffalo Sabres"}, {"id": "788cd7883414c082973a9cf64ecf502b", "sport_key": "icehockey_nhl", "sport_title": "NHL", "commence_time": "2023-12-03T00:00:00Z", "home_team": "Montr\u00e9al Canadiens", "away_team": "Detroit Red Wings"}, {"id": "d1c87bc725134128bc5ce41add711fed", "sport_key": "icehockey_nhl", "sport_title": "NHL", "commence_time": "2023-12-03T00:00:00Z", "home_team": "Ottawa Senators", "away_team": "Seattle Kraken"}, {"id": "18287a4a6b8ef4d99e19fe43769b2737", "sport_key": "icehockey_nhl", "sport_title": "NHL", "commence_time": "2023-12-03T00:00:00Z", "home_team": "Pittsburgh Penguins", "away_team": "Philadelphia Flyers"}, {"id": "f6bf32925b26193ac8285a667c98a962", "sport_key": "icehockey_nhl", "sport_title": "NHL", "commence_time": "2023-12-03T02:00:00Z", "home_team": "Arizona Coyotes", "away_team": "St Louis Blues"}, {"id": "988f099ad199dbe0ca772b40467e0346", "sport_key": "icehockey_nhl", "sport_title": "NHL", "commence_time": "2023-12-03T03:00:00Z", "home_team": "Anaheim Ducks", "away_team": "Colorado Avalanche"}, {"id": "683b9f7032fc3a6d2a8ddd1dfeb617a1", "sport_key": "icehockey_nhl", "sport_title": "NHL", "commence_time": "2023-12-03T03:00:00Z", "home_team": "Calgary Flames", "away_team": "Vancouver Canucks"}, {"id": "ae976283901fb066236a53db6ed089ba", "sport_key": "icehockey_nhl", "sport_title": "NHL", "commence_time": "2023-12-03T03:00:00Z", "home_team": "Vegas Golden Knights", "away_team": "Washington Capitals"}]}