{"timestamp": "2023-02-17T16:55:39Z", "previous_timestamp": "2023-02-17T16:50:39Z", "next_timestamp": "2023-02-17T17:00:38Z", "data": [{"id": "9214a1c432a60d1ed33b42690c5c7608", "sport_key": "icehockey_nhl", "sport_title": "NHL", "commence_time": "2023-02-18T00:00:00Z", "home_team": "Ottawa Senators", "away_team": "Chicago Blackhawks"}, {"id": "3cfc045b5cff869911ba8216ca6f3fdc", "sport_key": "icehockey_nhl", "sport_title": "NHL", "commence_time": "2023-02-18T00:00:00Z", "home_team": "New York Islanders", "away_team": "Pittsburgh Penguins"}, {"id": "6cfea1bb362a5ede971f3d3ff935e56f", "sport_key": "icehockey_nhl", "sport_title": "NHL", "commence_time": "2023-02-18T01:00:00Z", "home_team": "Minnesota Wild", "away_team": "Dallas Stars"}, {"id": "c5df5c0e92c88b2117275e6fdc85f4f5", "sport_key": "icehockey_nhl", "sport_title": "NHL", "commence_time": "2023-02-18T02:00:00Z", "home_team": "Anaheim Ducks", "away_team": "Los Angeles Kings"}, {"id": "52fd6ec39e43bce54aea8fa8d81d520f", "sport_key": "icehockey_nhl", "sport_title": "NHL", "commence_time": "2023-02-18T02:00:00Z", "home_team": "Edmonton Oilers", "away_team": "New York Rangers"}, {"id": "acb536a00a3e94a79dc2f9ced9dd2363", "sport_key": "icehockey_nhl", "sport_title": "NHL", "commence_time": "2023-02-18T19:00:00Z", "home_team": "St Louis Blues", "away_team": "Colorado Avalanche"}, {"id": "a8ec126aa74dba0bdeec091d9f4aa48a", "sport_key": "icehockey_nhl", "sport_title": "NHL", "commence_time": "2023-02-18T19:00:00Z", "home_team": "Nashville Predators", "away_team": "Florida Panthers"}, {"id": "bfba9275f48528a4febf3be36cb83566", "sport_key": "icehockey_nhl", "sport_title": "NHL", "commence_time": "2023-02-18T22:00:00Z", "home_team": "Boston Bruins", "away_team": "New York Islanders"}, {"id": "1e0d11ee9f4fbc92a0d86d77b05e9db0", "sport_key": "icehockey_nhl", "sport_title": "NHL", "commence_time": "2023-02-18T22:30:00Z", "home_team": "Pittsburgh Penguins", "away_team": "New Jersey Devils"}, {"id": "88aed512f7f0b04f192b0681ebd5e921", "sport_key": "icehockey_nhl", "sport_title": "NHL", "commence_time": "2023-02-18T23:00:00Z", "home_team": "Dallas Stars", "away_team": "Columbus Blue Jackets"}, {"id": "fe0e1fd168da4ae548d6203f6b853b3b", "sport_key": "icehockey_nhl", "sport_title": "NHL", "commence_time": "2023-02-19T00:00:00Z", "home_team": "Toronto Maple Leafs", "away_team": "Montr\u00e9al Canadiens"}, {"id": "0ff6711ef0acaeb76d489319abe1ec12", "sport_key": "icehockey_nhl", "sport_title": "NHL", "commence_time": "2023-02-19T01:00:00Z", "home_team": "Carolina Hurricanes", "away_team": "Washington Capitals"}, {"id": "23a307bcb82fdc0d7e4c99332fa9037f", "sport_key": "icehockey_nhl", "sport_title": "NHL", "commence_time": "2023-02-19T03:00:00Z", "home_team": "Calgary Flames", "away_team": "New York Rangers"}, {"id": "7f53123bef7b49887bd7c6d1763bfb85", "sport_key": "icehockey_nhl", "sport_title": "NHL", "commence_time": "2023-02-19T03:00:00Z", "home_team": "Vancouver Canucks", "away_team": "Philadelphia Flyers"}, {"id": "ec4a7b7ab96ac4925bfc7f7afbdae432", "sport_key": "icehockey_nhl", "sport_title": "NHL", "commence_time": "2023-02-19T03:30:00Z", "home_team": "Los Angeles Kings", "away_team": "Arizona Coyotes"}, {"id": "b5b031134882767a2dcc6bbc94da284f", "sport_key": "icehockey_nhl", "sport_title": "NHL", "commence_time": "2023-02-19T03:30:00Z", "home_team": "San Jose Sharks", "away_team": "Buffalo Sabres"}, {"id": "2f927bbc99173703117d963895d57917", "sport_key": "icehockey_nhl", "sport_title": "NHL", "commence_time": "2023-02-19T03:30:00Z", "home_team": "Seattle Kraken", "away_team": "Detroit Red Wings"}, {"id": "d5ee3f69f2c3a981c2605f07ec59c6b5", "sport_key": "icehockey_nhl", "sport_title": "NHL", "commence_time": "2023-02-19T03:30:00Z", "home_team": "Vegas Golden Knights", "away_team": "Tampa Bay Lightning"}]}