{"timestamp": "2024-05-31T16:55:38Z", "previous_timestamp": "2024-05-31T16:50:38Z", "next_timestamp": "2024-05-31T17:00:38Z", "data": [{"id": "44eb2ab1727245ca4445455e8883013f", "sport_key": "icehockey_nhl", "sport_title": "NHL", "commence_time": "2024-06-01T00:40:00Z", "home_team": "Dallas Stars", "away_team": "Edmonton Oilers"}, {"id": "0eeb3f7309d1ced8f5b18554ad84b0bd", "sport_key": "icehockey_nhl", "sport_title": "NHL", "commence_time": "2024-06-02T00:10:00Z", "home_team": "Florida Panthers", "away_team": "New York Rangers"}]}