{"timestamp": "2022-12-30T03:10:38Z", "previous_timestamp": "2022-12-30T03:05:39Z", "next_timestamp": "2022-12-30T03:15:39Z", "data": {"id": "1e39fa9fcc167e3be437b774f74d639a", "sport_key": "icehockey_nhl", "sport_title": "NHL", "commence_time": "2022-12-30T03:30:00Z", "home_team": "San Jose Sharks", "away_team": "Philadelphia Flyers", "bookmakers": [{"key": "barstool", "title": "Barstool Sportsbook", "last_update": "2022-12-30T03:10:01Z", "markets": [{"key": "totals", "last_update": "2022-12-30T03:10:01Z", "outcomes": [{"name": "Over", "price": 1.81, "point": 6.0}, {"name": "Under", "price": 2.02, "point": 6.0}]}]}, {"key": "sport888", "title": "888sport", "last_update": "2022-12-30T03:10:19Z", "markets": [{"key": "totals", "last_update": "2022-12-30T03:10:19Z", "outcomes": [{"name": "Over", "price": 1.65, "point": 5.5}, {"name": "Under", "price": 2.3, "point": 5.5}]}]}, {"key": "sugarhouse", "title": "SugarHouse", "last_update": "2022-12-30T03:10:20Z", "markets": [{"key": "totals", "last_update": "2022-12-30T03:10:20Z", "outcomes": [{"name": "Over", "price": 1.82, "point": 6.0}, {"name": "Under", "price": 2.04, "point": 6.0}]}]}, {"key": "twinspires", "title": "TwinSpires", "last_update": "2022-12-30T03:10:20Z", "markets": [{"key": "totals", "last_update": "2022-12-30T03:10:20Z", "outcomes": [{"name": "Over", "price": 1.81, "point": 6.0}, {"name": "Under", "price": 2.02, "point": 6.0}]}]}, {"key": "betrivers", "title": "BetRivers", "last_update": "2022-12-30T03:10:19Z", "markets": [{"key": "totals", "last_update": "2022-12-30T03:10:19Z", "outcomes": [{"name": "Over", "price": 1.82, "point": 6.0}, {"name": "Under", "price": 2.04, "point": 6.0}]}]}, {"key": "unibet_us", "title": "Unibet", "last_update": "2022-12-30T03:10:21Z", "markets": [{"key": "totals", "last_update": "2022-12-30T03:10:21Z", "outcomes": [{"name": "Over", "price": 1.81, "point": 6.0}, {"name": "Under", "price": 2.02, "point": 6.0}]}]}, {"key": "onexbet", "title": "1xBet", "last_update": "2022-12-30T03:08:49Z", "markets": [{"key": "totals", "last_update": "2022-12-30T03:08:49Z", "outcomes": [{"name": "Over", "price": 2.29, "point": 6.5}, {"name": "Under", "price": 1.73, "point": 6.5}]}]}, {"key": "lowvig", "title": "LowVig.ag", "last_update": "2022-12-30T03:10:22Z", "markets": [{"key": "totals", "last_update": "2022-12-30T03:10:22Z", "outcomes": [{"name": "Over", "price": 2.07, "point": 6.5}, {"name": "Under", "price": 1.85, "point": 6.5}]}]}, {"key": "betonlineag", "title": "BetOnline.ag", "last_update": "2022-12-30T03:10:01Z", "markets": [{"key": "totals", "last_update": "2022-12-30T03:10:01Z", "outcomes": [{"name": "Over", "price": 2.06, "point": 6.5}, {"name": "Under", "price": 1.84, "point": 6.5}]}]}, {"key": "betus", "title": "BetUS", "last_update": "2022-12-30T03:10:01Z", "markets": [{"key": "totals", "last_update": "2022-12-30T03:10:01Z", "outcomes": [{"name": "Over", "price": 2.0, "point": 6.5}, {"name": "Under", "price": 1.83, "point": 6.5}]}]}, {"key": "williamhill_us", "title": "William Hill (US)", "last_update": "2022-12-30T03:10:19Z", "markets": [{"key": "totals", "last_update": "2022-12-30T03:10:19Z", "outcomes": [{"name": "Over", "price": 2.0, "point": 6.5}, {"name": "Under", "price": 1.83, "point": 6.5}]}]}, {"key": "draftkings", "title": "DraftKings", "last_update": "2022-12-30T03:10:19Z", "markets": [{"key": "totals", "last_update": "2022-12-30T03:10:19Z", "outcomes": [{"name": "Over", "price": 2.0, "point": 6.5}, {"name": "Under", "price": 1.83, "point": 6.5}]}]}, {"key": "gtbets", "title": "GTbets", "last_update": "2022-12-30T03:10:19Z", "markets": [{"key": "totals", "last_update": "2022-12-30T03:10:19Z", "outcomes": [{"name": "Over", "price": 2.0, "point": 6.5}, {"name": "Under", "price": 1.83, "point": 6.5}]}]}, {"key": "fanduel", "title": "FanDuel", "last_update": "2022-12-30T03:10:19Z", "markets": [{"key": "totals", "last_update": "2022-12-30T03:10:19Z", "outcomes": [{"name": "Over", "price": 2.02, "point": 6.5}, {"name": "Under", "price": 1.81, "point": 6.5}]}]}, {"key": "pointsbetus", "title": "PointsBet (US)", "last_update": "2022-12-30T03:10:08Z", "markets": [{"key": "totals", "last_update": "2022-12-30T03:10:08Z", "outcomes": [{"name": "Over", "price": 1.95, "point": 6.5}, {"name": "Under", "price": 1.87, "point": 6.5}]}]}, {"key": "wynnbet", "title": "WynnBET", "last_update": "2022-12-30T03:10:20Z", "markets": [{"key": "totals", "last_update": "2022-12-30T03:10:20Z", "outcomes": [{"name": "Over", "price": 1.95, "point": 6.5}, {"name": "Under", "price": 1.87, "point": 6.5}]}]}, {"key": "betmgm", "title": "BetMGM", "last_update": "2022-12-30T03:10:02Z", "markets": [{"key": "totals", "last_update": "2022-12-30T03:10:02Z", "outcomes": [{"name": "Over", "price": 2.0, "point": 6.5}, {"name": "Under", "price": 1.83, "point": 6.5}]}]}, {"key": "pinnacle", "title": "Pinnacle", "last_update": "2022-12-30T03:10:20Z", "markets": [{"key": "totals", "last_update": "2022-12-30T03:10:20Z", "outcomes": [{"name": "Over", "price": 2.03, "point": 6.5}, {"name": "Under", "price": 1.86, "point": 6.5}]}]}, {"key": "bovada", "title": "Bovada", "last_update": "2022-12-30T03:10:02Z", "markets": [{"key": "totals", "last_update": "2022-12-30T03:10:02Z", "outcomes": [{"name": "Over", "price": 1.95, "point": 6.5}, {"name": "Under", "price": 1.87, "point": 6.5}]}]}, {"key": "foxbet", "title": "FOX Bet", "last_update": "2022-12-30T03:10:19Z", "markets": [{"key": "totals", "last_update": "2022-12-30T03:10:19Z", "outcomes": [{"name": "Over", "price": 2.0, "point": 6.5}, {"name": "Under", "price": 1.75, "point": 6.5}]}]}, {"key": "mybookieag", "title": "MyBookie.ag", "last_update": "2022-12-30T03:10:01Z", "markets": [{"key": "totals", "last_update": "2022-12-30T03:10:01Z", "outcomes": [{"name": "Over", "price": 2.01, "point": 6.5}, {"name": "Under", "price": 1.81, "point": 6.5}]}]}, {"key": "matchbook", "title": "Matchbook", "last_update": "2022-12-30T03:10:18Z", "markets": [{"key": "totals", "last_update": "2022-12-30T03:10:18Z", "outcomes": [{"name": "Over", "price": 1.71, "point": 5.5}, {"name": "Under", "price": 2.28, "point": 5.5}]}]}]}}