{"timestamp": "2023-12-19T00:10:39Z", "previous_timestamp": "2023-12-19T00:05:39Z", "next_timestamp": "2023-12-19T00:15:38Z", "data": {"id": "661db2e0fe3612d58769df44a87c36f1", "sport_key": "icehockey_nhl", "sport_title": "NHL", "commence_time": "2023-12-19T00:30:00Z", "home_team": "Winnipeg Jets", "away_team": "Montr\u00e9al Canadiens", "bookmakers": [{"key": "sport888", "title": "888sport", "last_update": "2023-12-19T00:09:55Z", "markets": [{"key": "totals", "last_update": "2023-12-19T00:09:55Z", "outcomes": [{"name": "Over", "price": 1.75, "point": 5.5}, {"name": "Under", "price": 2.05, "point": 5.5}]}]}, {"key": "unibet_us", "title": "Unibet", "last_update": "2023-12-19T00:10:34Z", "markets": [{"key": "totals", "last_update": "2023-12-19T00:10:34Z", "outcomes": [{"name": "Over", "price": 1.95, "point": 6.0}, {"name": "Under", "price": 1.87, "point": 6.0}]}]}, {"key": "windcreek", "title": "Wind Creek", "last_update": "2023-12-19T00:10:32Z", "markets": [{"key": "totals", "last_update": "2023-12-19T00:10:32Z", "outcomes": [{"name": "Over", "price": 1.79, "point": 3.5}, {"name": "Under", "price": 1.99, "point": 3.5}]}]}, {"key": "onexbet", "title": "1xBet", "last_update": "2023-12-19T00:09:04Z", "markets": [{"key": "totals", "last_update": "2023-12-19T00:09:04Z", "outcomes": [{"name": "Over", "price": 1.79, "point": 5.5}, {"name": "Under", "price": 2.19, "point": 5.5}]}]}, {"key": "betrivers", "title": "BetRivers", "last_update": "2023-12-19T00:10:21Z", "markets": [{"key": "totals", "last_update": "2023-12-19T00:10:21Z", "outcomes": [{"name": "Over", "price": 1.95, "point": 6.0}, {"name": "Under", "price": 1.87, "point": 6.0}]}]}, {"key": "betparx", "title": "betPARX", "last_update": "2023-12-19T00:10:29Z", "markets": [{"key": "totals", "last_update": "2023-12-19T00:10:29Z", "outcomes": [{"name": "Over", "price": 1.95, "point": 6.0}, {"name": "Under", "price": 1.87, "point": 6.0}]}]}, {"key": "sisportsbook", "title": "SI Sportsbook", "last_update": "2023-12-19T00:10:04Z", "markets": [{"key": "totals", "last_update": "2023-12-19T00:10:04Z", "outcomes": [{"name": "Over", "price": 1.73, "point": 5.5}, {"name": "Under", "price": 2.1, "point": 5.5}]}]}, {"key": "unibet_eu", "title": "Unibet", "last_update": "2023-12-19T00:10:11Z", "markets": [{"key": "totals", "last_update": "2023-12-19T00:10:11Z", "outcomes": [{"name": "Over", "price": 2.1, "point": 6.0}, {"name": "Under", "price": 1.75, "point": 6.0}]}]}, {"key": "fanduel", "title": "FanDuel", "last_update": "2023-12-19T00:10:03Z", "markets": [{"key": "totals", "last_update": "2023-12-19T00:10:03Z", "outcomes": [{"name": "Over", "price": 1.75, "point": 5.5}, {"name": "Under", "price": 2.1, "point": 5.5}]}]}, {"key": "fliff", "title": "Fliff", "last_update": "2023-12-19T00:01:21Z", "markets": [{"key": "totals", "last_update": "2023-12-19T00:01:21Z", "outcomes": [{"name": "Over", "price": 1.87, "point": 6.0}, {"name": "Under", "price": 1.83, "point": 6.0}]}]}, {"key": "lowvig", "title": "LowVig.ag", "last_update": "2023-12-19T00:10:24Z", "markets": [{"key": "totals", "last_update": "2023-12-19T00:10:24Z", "outcomes": [{"name": "Over", "price": 2.0, "point": 6.0}, {"name": "Under", "price": 1.86, "point": 6.0}]}]}, {"key": "betonlineag", "title": "BetOnline.ag", "last_update": "2023-12-19T00:10:34Z", "markets": [{"key": "totals", "last_update": "2023-12-19T00:10:34Z", "outcomes": [{"name": "Over", "price": 2.0, "point": 6.0}, {"name": "Under", "price": 1.86, "point": 6.0}]}]}, {"key": "draftkings", "title": "DraftKings", "last_update": "2023-12-19T00:10:13Z", "markets": [{"key": "totals", "last_update": "2023-12-19T00:10:13Z", "outcomes": [{"name": "Over", "price": 2.02, "point": 6.0}, {"name": "Under", "price": 1.82, "point": 6.0}]}]}, {"key": "livescorebet_eu", "title": "LiveScore Bet (EU)", "last_update": "2023-12-19T00:10:27Z", "markets": [{"key": "totals", "last_update": "2023-12-19T00:10:27Z", "outcomes": [{"name": "Over", "price": 2.05, "point": 6.0}, {"name": "Under", "price": 1.82, "point": 6.0}]}]}, {"key": "williamhill_us", "title": "Caesars", "last_update": "2023-12-19T00:10:36Z", "markets": [{"key": "totals", "last_update": "2023-12-19T00:10:36Z", "outcomes": [{"name": "Over", "price": 1.95, "point": 6.0}, {"name": "Under", "price": 1.87, "point": 6.0}]}]}, {"key": "betmgm", "title": "BetMGM", "last_update": "2023-12-19T00:10:07Z", "markets": [{"key": "totals", "last_update": "2023-12-19T00:10:07Z", "outcomes": [{"name": "Over", "price": 2.0, "point": 6.0}, {"name": "Under", "price": 1.83, "point": 6.0}]}]}, {"key": "betus", "title": "BetUS", "last_update": "2023-12-19T00:10:06Z", "markets": [{"key": "totals", "last_update": "2023-12-19T00:10:06Z", "outcomes": [{"name": "Over", "price": 1.95, "point": 6.0}, {"name": "Under", "price": 1.87, "point": 6.0}]}]}, {"key": "pinnacle", "title": "Pinnacle", "last_update": "2023-12-19T00:10:04Z", "markets": [{"key": "totals", "last_update": "2023-12-19T00:10:04Z", "outcomes": [{"name": "Over", "price": 2.0, "point": 6.0}, {"name": "Under", "price": 1.88, "point": 6.0}]}]}, {"key": "bovada", "title": "Bovada", "last_update": "2023-12-19T00:10:20Z", "markets": [{"key": "totals", "last_update": "2023-12-19T00:10:20Z", "outcomes": [{"name": "Over", "price": 1.97, "point": 6.0}, {"name": "Under", "price": 1.85, "point": 6.0}]}]}, {"key": "espnbet", "title": "ESPN BET", "last_update": "2023-12-19T00:10:31Z", "markets": [{"key": "totals", "last_update": "2023-12-19T00:10:31Z", "outcomes": [{"name": "Over", "price": 1.77, "point": 5.5}, {"name": "Under", "price": 2.1, "point": 5.5}]}]}, {"key": "hardrockbet", "title": "Hard Rock Bet", "last_update": "2023-12-19T00:10:29Z", "markets": [{"key": "totals", "last_update": "2023-12-19T00:10:29Z", "outcomes": [{"name": "Over", "price": 1.71, "point": 5.5}, {"name": "Under", "price": 2.15, "point": 5.5}]}]}, {"key": "pointsbetus", "title": "PointsBet (US)", "last_update": "2023-12-19T00:09:49Z", "markets": [{"key": "totals", "last_update": "2023-12-19T00:09:49Z", "outcomes": [{"name": "Over", "price": 2.15, "point": 6.5}, {"name": "Under", "price": 1.71, "point": 6.5}]}]}, {"key": "matchbook", "title": "Matchbook", "last_update": "2023-12-19T00:10:31Z", "markets": [{"key": "totals", "last_update": "2023-12-19T00:10:31Z", "outcomes": [{"name": "Over", "price": 1.78, "point": 5.5}, {"name": "Under", "price": 2.18, "point": 5.5}]}]}, {"key": "everygame", "title": "Everygame", "last_update": "2023-12-19T00:10:29Z", "markets": [{"key": "totals", "last_update": "2023-12-19T00:10:29Z", "outcomes": [{"name": "Over", "price": 1.95, "point": 6.0}, {"name": "Under", "price": 1.87, "point": 6.0}]}]}]}}