{"timestamp": "2023-10-14T19:40:40Z", "previous_timestamp": "2023-10-14T19:35:41Z", "next_timestamp": "2023-10-14T19:45:41Z", "data": {"id": "bda782e17c503c8c3057ac90d7aece0e", "sport_key": "icehockey_nhl", "sport_title": "NHL", "commence_time": "2023-10-14T20:08:00Z", "home_team": "Winnipeg Jets", "away_team": "Florida Panthers", "bookmakers": [{"key": "draftkings", "title": "DraftKings", "last_update": "2023-10-14T19:40:18Z", "markets": [{"key": "totals", "last_update": "2023-10-14T19:40:18Z", "outcomes": [{"name": "Over", "price": 1.83, "point": 6.5}, {"name": "Under", "price": 2.0, "point": 6.5}]}]}, {"key": "sisportsbook", "title": "SI Sportsbook", "last_update": "2023-10-14T19:40:07Z", "markets": [{"key": "totals", "last_update": "2023-10-14T19:40:07Z", "outcomes": [{"name": "Over", "price": 1.8, "point": 6.5}, {"name": "Under", "price": 2.0, "point": 6.5}]}]}, {"key": "sport888", "title": "888sport", "last_update": "2023-10-14T19:40:07Z", "markets": [{"key": "totals", "last_update": "2023-10-14T19:40:07Z", "outcomes": [{"name": "Over", "price": 1.8, "point": 6.5}, {"name": "Under", "price": 2.0, "point": 6.5}]}]}, {"key": "pointsbetus", "title": "PointsBet (US)", "last_update": "2023-10-14T19:39:58Z", "markets": [{"key": "totals", "last_update": "2023-10-14T19:39:58Z", "outcomes": [{"name": "Over", "price": 1.77, "point": 6.5}, {"name": "Under", "price": 2.0, "point": 6.5}]}]}, {"key": "twinspires", "title": "TwinSpires", "last_update": "2023-10-14T19:40:07Z", "markets": [{"key": "totals", "last_update": "2023-10-14T19:40:07Z", "outcomes": [{"name": "Over", "price": 1.87, "point": 6.5}, {"name": "Under", "price": 1.94, "point": 6.5}]}]}, {"key": "betrivers", "title": "BetRivers", "last_update": "2023-10-14T19:40:08Z", "markets": [{"key": "totals", "last_update": "2023-10-14T19:40:08Z", "outcomes": [{"name": "Over", "price": 1.87, "point": 6.5}, {"name": "Under", "price": 1.94, "point": 6.5}]}]}, {"key": "betparx", "title": "betPARX", "last_update": "2023-10-14T19:40:19Z", "markets": [{"key": "totals", "last_update": "2023-10-14T19:40:19Z", "outcomes": [{"name": "Over", "price": 1.87, "point": 6.5}, {"name": "Under", "price": 1.94, "point": 6.5}]}]}, {"key": "unibet_us", "title": "Unibet", "last_update": "2023-10-14T19:40:25Z", "markets": [{"key": "totals", "last_update": "2023-10-14T19:40:25Z", "outcomes": [{"name": "Over", "price": 1.87, "point": 6.5}, {"name": "Under", "price": 1.94, "point": 6.5}]}]}, {"key": "fanduel", "title": "FanDuel", "last_update": "2023-10-14T19:40:25Z", "markets": [{"key": "totals", "last_update": "2023-10-14T19:40:25Z", "outcomes": [{"name": "Over", "price": 1.88, "point": 6.5}, {"name": "Under", "price": 1.94, "point": 6.5}]}]}, {"key": "williamhill_us", "title": "Caesars", "last_update": "2023-10-14T19:40:23Z", "markets": [{"key": "totals", "last_update": "2023-10-14T19:40:22Z", "outcomes": [{"name": "Over", "price": 1.87, "point": 6.5}, {"name": "Under", "price": 1.95, "point": 6.5}]}]}, {"key": "lowvig", "title": "LowVig.ag", "last_update": "2023-10-14T19:40:10Z", "markets": [{"key": "totals", "last_update": "2023-10-14T19:40:10Z", "outcomes": [{"name": "Over", "price": 1.9, "point": 6.5}, {"name": "Under", "price": 1.95, "point": 6.5}]}]}, {"key": "betonlineag", "title": "BetOnline.ag", "last_update": "2023-10-14T19:40:23Z", "markets": [{"key": "totals", "last_update": "2023-10-14T19:40:23Z", "outcomes": [{"name": "Over", "price": 1.9, "point": 6.5}, {"name": "Under", "price": 1.95, "point": 6.5}]}]}, {"key": "pinnacle", "title": "Pinnacle", "last_update": "2023-10-14T19:40:07Z", "markets": [{"key": "totals", "last_update": "2023-10-14T19:40:07Z", "outcomes": [{"name": "Over", "price": 1.88, "point": 6.5}, {"name": "Under", "price": 2.01, "point": 6.5}]}]}, {"key": "betmgm", "title": "BetMGM", "last_update": "2023-10-14T19:39:49Z", "markets": [{"key": "totals", "last_update": "2023-10-14T19:39:49Z", "outcomes": [{"name": "Over", "price": 1.87, "point": 6.5}, {"name": "Under", "price": 1.95, "point": 6.5}]}]}, {"key": "bovada", "title": "Bovada", "last_update": "2023-10-14T19:40:25Z", "markets": [{"key": "totals", "last_update": "2023-10-14T19:40:25Z", "outcomes": [{"name": "Over", "price": 1.87, "point": 6.5}, {"name": "Under", "price": 1.95, "point": 6.5}]}]}, {"key": "matchbook", "title": "Matchbook", "last_update": "2023-10-14T19:40:26Z", "markets": [{"key": "totals", "last_update": "2023-10-14T19:40:26Z", "outcomes": [{"name": "Over", "price": 1.94, "point": 6.5}, {"name": "Under", "price": 1.98, "point": 6.5}]}]}, {"key": "betus", "title": "BetUS", "last_update": "2023-10-14T19:39:48Z", "markets": [{"key": "totals", "last_update": "2023-10-14T19:39:48Z", "outcomes": [{"name": "Over", "price": 1.87, "point": 6.5}, {"name": "Under", "price": 1.95, "point": 6.5}]}]}, {"key": "everygame", "title": "Everygame", "last_update": "2023-10-14T19:39:54Z", "markets": [{"key": "totals", "last_update": "2023-10-14T19:39:54Z", "outcomes": [{"name": "Over", "price": 1.87, "point": 6.5}, {"name": "Under", "price": 1.95, "point": 6.5}]}]}]}}