{"timestamp": "2025-03-05T01:40:39Z", "previous_timestamp": "2025-03-05T01:35:39Z", "next_timestamp": "2025-03-05T01:45:38Z", "data": {"id": "6ffbee32ef41d37ead97faf23fe035e5", "sport_key": "icehockey_nhl", "sport_title": "NHL", "commence_time": "2025-03-05T02:00:00Z", "home_team": "Colorado Avalanche", "away_team": "Pittsburgh Penguins", "bookmakers": [{"key": "onexbet", "title": "1xBet", "last_update": "2025-03-05T01:40:06Z", "markets": [{"key": "totals", "last_update": "2025-03-05T01:40:06Z", "outcomes": [{"name": "Over", "price": 2.15, "point": 6.5}, {"name": "Under", "price": 1.77, "point": 6.5}]}]}, {"key": "betrivers", "title": "BetRivers", "last_update": "2025-03-05T01:40:08Z", "markets": [{"key": "totals", "last_update": "2025-03-05T01:40:08Z", "outcomes": [{"name": "Over", "price": 1.93, "point": 6.5}, {"name": "Under", "price": 1.88, "point": 6.5}]}]}, {"key": "fliff", "title": "Fliff", "last_update": "2025-03-05T01:40:08Z", "markets": [{"key": "totals", "last_update": "2025-03-05T01:40:08Z", "outcomes": [{"name": "Over", "price": 1.87, "point": 6.5}, {"name": "Under", "price": 1.83, "point": 6.5}]}]}, {"key": "ballybet", "title": "Bally Bet", "last_update": "2025-03-05T01:40:07Z", "markets": [{"key": "totals", "last_update": "2025-03-05T01:40:07Z", "outcomes": [{"name": "Over", "price": 1.93, "point": 6.5}, {"name": "Under", "price": 1.88, "point": 6.5}]}]}, {"key": "betparx", "title": "betPARX", "last_update": "2025-03-05T01:40:07Z", "markets": [{"key": "totals", "last_update": "2025-03-05T01:40:07Z", "outcomes": [{"name": "Over", "price": 1.93, "point": 6.5}, {"name": "Under", "price": 1.88, "point": 6.5}]}]}, {"key": "unibet_eu", "title": "Unibet", "last_update": "2025-03-05T01:40:07Z", "markets": [{"key": "totals", "last_update": "2025-03-05T01:40:07Z", "outcomes": [{"name": "Over", "price": 1.8, "point": 6.0}, {"name": "Under", "price": 2.02, "point": 6.0}]}]}, {"key": "fanduel", "title": "FanDuel", "last_update": "2025-03-05T01:40:07Z", "markets": [{"key": "totals", "last_update": "2025-03-05T01:40:07Z", "outcomes": [{"name": "Over", "price": 1.91, "point": 6.5}, {"name": "Under", "price": 1.91, "point": 6.5}]}]}, {"key": "draftkings", "title": "DraftKings", "last_update": "2025-03-05T01:40:06Z", "markets": [{"key": "totals", "last_update": "2025-03-05T01:40:06Z", "outcomes": [{"name": "Over", "price": 1.89, "point": 6.5}, {"name": "Under", "price": 1.93, "point": 6.5}]}]}, {"key": "betonlineag", "title": "BetOnline.ag", "last_update": "2025-03-05T01:40:06Z", "markets": [{"key": "totals", "last_update": "2025-03-05T01:40:06Z", "outcomes": [{"name": "Over", "price": 1.91, "point": 6.5}, {"name": "Under", "price": 1.94, "point": 6.5}]}]}, {"key": "lowvig", "title": "LowVig.ag", "last_update": "2025-03-05T01:40:06Z", "markets": [{"key": "totals", "last_update": "2025-03-05T01:40:06Z", "outcomes": [{"name": "Over", "price": 1.91, "point": 6.5}, {"name": "Under", "price": 1.94, "point": 6.5}]}]}, {"key": "gtbets", "title": "GTbets", "last_update": "2025-03-05T01:40:08Z", "markets": [{"key": "totals", "last_update": "2025-03-05T01:40:08Z", "outcomes": [{"name": "Over", "price": 1.91, "point": 6.5}, {"name": "Under", "price": 1.91, "point": 6.5}]}]}, {"key": "williamhill_us", "title": "Caesars", "last_update": "2025-03-05T01:38:35Z", "markets": [{"key": "totals", "last_update": "2025-03-05T01:38:35Z", "outcomes": [{"name": "Over", "price": 1.91, "point": 6.5}, {"name": "Under", "price": 1.91, "point": 6.5}]}]}, {"key": "espnbet", "title": "ESPN BET", "last_update": "2025-03-05T01:40:08Z", "markets": [{"key": "totals", "last_update": "2025-03-05T01:40:08Z", "outcomes": [{"name": "Over", "price": 1.91, "point": 6.5}, {"name": "Under", "price": 1.91, "point": 6.5}]}]}, {"key": "betus", "title": "BetUS", "last_update": "2025-03-05T01:40:07Z", "markets": [{"key": "totals", "last_update": "2025-03-05T01:40:07Z", "outcomes": [{"name": "Over", "price": 1.87, "point": 6.5}, {"name": "Under", "price": 1.95, "point": 6.5}]}]}, {"key": "pinnacle", "title": "Pinnacle", "last_update": "2025-03-05T01:40:06Z", "markets": [{"key": "totals", "last_update": "2025-03-05T01:40:06Z", "outcomes": [{"name": "Over", "price": 1.95, "point": 6.5}, {"name": "Under", "price": 1.93, "point": 6.5}]}]}, {"key": "bovada", "title": "Bovada", "last_update": "2025-03-05T01:25:59Z", "markets": [{"key": "totals", "last_update": "2025-03-05T01:25:59Z", "outcomes": [{"name": "Over", "price": 1.91, "point": 6.5}, {"name": "Under", "price": 1.91, "point": 6.5}]}]}, {"key": "fanatics", "title": "Fanatics", "last_update": "2025-03-05T01:40:08Z", "markets": [{"key": "totals", "last_update": "2025-03-05T01:40:08Z", "outcomes": [{"name": "Over", "price": 1.91, "point": 6.5}, {"name": "Under", "price": 1.91, "point": 6.5}]}]}, {"key": "hardrockbet", "title": "Hard Rock Bet", "last_update": "2025-03-05T01:40:07Z", "markets": [{"key": "totals", "last_update": "2025-03-05T01:40:07Z", "outcomes": [{"name": "Over", "price": 1.91, "point": 6.5}, {"name": "Under", "price": 1.91, "point": 6.5}]}]}, {"key": "betmgm", "title": "BetMGM", "last_update": "2025-03-05T01:38:36Z", "markets": [{"key": "totals", "last_update": "2025-03-05T01:38:36Z", "outcomes": [{"name": "Over", "price": 1.91, "point": 6.5}, {"name": "Under", "price": 1.91, "point": 6.5}]}]}, {"key": "tipico_de", "title": "Tipico", "last_update": "2025-03-05T01:40:08Z", "markets": [{"key": "totals", "last_update": "2025-03-05T01:40:08Z", "outcomes": [{"name": "Over", "price": 2.05, "point": 6.5}, {"name": "Under", "price": 1.67, "point": 6.5}]}]}, {"key": "matchbook", "title": "Matchbook", "last_update": "2025-03-05T01:40:06Z", "markets": [{"key": "totals", "last_update": "2025-03-05T01:40:06Z", "outcomes": [{"name": "Over", "price": 2.84, "point": 7.5}, {"name": "Under", "price": 1.45, "point": 7.5}]}]}, {"key": "windcreek", "title": "Wind Creek", "last_update": "2025-03-05T01:38:36Z", "markets": [{"key": "totals", "last_update": "2025-03-05T01:38:36Z", "outcomes": [{"name": "Over", "price": 1.69, "point": 6.0}, {"name": "Under", "price": 2.15, "point": 6.0}]}]}, {"key": "sport888", "title": "888sport", "last_update": "2025-03-05T01:40:06Z", "markets": [{"key": "totals", "last_update": "2025-03-05T01:40:06Z", "outcomes": [{"name": "Over", "price": 1.9, "point": 6.5}, {"name": "Under", "price": 1.9, "point": 6.5}]}]}, {"key": "coolbet", "title": "Coolbet", "last_update": "2025-03-05T01:40:08Z", "markets": [{"key": "totals", "last_update": "2025-03-05T01:40:08Z", "outcomes": [{"name": "Over", "price": 1.91, "point": 6.5}, {"name": "Under", "price": 1.91, "point": 6.5}]}]}, {"key": "everygame", "title": "Everygame", "last_update": "2025-03-05T01:40:08Z", "markets": [{"key": "totals", "last_update": "2025-03-05T01:40:08Z", "outcomes": [{"name": "Over", "price": 1.91, "point": 6.5}, {"name": "Under", "price": 1.91, "point": 6.5}]}]}]}}